PyLooper/__init__.py
PyLooper/api/__init__.py
PyLooper/api/run.py
PyLooper/common/Analyzer.py
PyLooper/common/Collector.py
PyLooper/common/Dataset.py
PyLooper/common/Module.py
PyLooper/common/__init__.py
PyLooper/hep/__init__.py
PyLooper/hep/cms/__init__.py
PyLooper/hep/cms/dataset/CMSDataset.py
PyLooper/hep/cms/dataset/MergedCMSDataset.py
PyLooper/hep/cms/dataset/__init__.py
PyLooper/hep/plotter/Plot.py
PyLooper/hep/plotter/Plotter.py
PyLooper/hep/plotter/__init__.py
PyLooper/hep/root/TFile.py
PyLooper/hep/root/__init__.py
PyLooper/ml/DataWrapper.py
PyLooper/ml/Training.py
PyLooper/ml/__init__.py
PyLooper/progressbar/ProgressBar.py
PyLooper/progressbar/ProgressReport.py
PyLooper/progressbar/__init__.py
PyLooper/site/__init__.py
PyLooper/stat/Hist1D.py
PyLooper/stat/__init__.py
PyLooper/utils/__init__.py
PyLooper/utils/mkdir_p.py
PyLooper-0.0.3.dist-info/LICENSE
PyLooper-0.0.3.dist-info/METADATA
PyLooper-0.0.3.dist-info/WHEEL
PyLooper-0.0.3.dist-info/entry_points.txt
PyLooper-0.0.3.dist-info/top_level.txt
PyLooper-0.0.3.dist-info/RECORD
