Metadata-Version: 2.1
Name: PyLooper
Version: 0.0.3
Summary: A general framework to analyse dataset that cannot be fit into memory in one go
Home-page: https://github.com/lucien1011/PyLooper
Author: K. H. Lo
Author-email: khl.lucien@gmail.com
License: MIT
Keywords: numpy  cuda  matplotlib tensorflow  hep  parallel-computing gpu-computing
Platform: UNKNOWN
